pydevmgr/__init__.py
pydevmgr/base/__init__.py
pydevmgr/base/config.py
pydevmgr/base/globalnode.py
pydevmgr/base/io.py
pydevmgr/base/tools.py
pydevmgr/base/uacom.py
pydevmgr/base/uadevice.py
pydevmgr/base/uainterface.py
pydevmgr/base/uamanager.py
pydevmgr/base/uanode.py
pydevmgr/base/uarpc.py
pydevmgr/base/uarpcinterface.py
pydevmgr/devices/__init__.py
pydevmgr/devices/adc.py
pydevmgr/devices/drot.py
pydevmgr/devices/lamp.py
pydevmgr/devices/motor.py
pydevmgr/devices/piezo.py
pydevmgr/devices/shutter.py
pydevmgr/devices/trk.py
pydevmgr/resources/mapActuator.yml
pydevmgr/resources/mapAdc.yml
pydevmgr/resources/mapCcc.yml
pydevmgr/resources/mapDevice.yml
pydevmgr/resources/mapDrot.yml
pydevmgr/resources/mapLakeshore224.yml
pydevmgr/resources/mapLamp.yml
pydevmgr/resources/mapMotor.yml
pydevmgr/resources/mapPiezo.yml
pydevmgr/resources/mapSensor.yml
pydevmgr/resources/mapShutter.yml
pydevmgr/resources/templateAdc.yml
pydevmgr/resources/templateDrot.yml
pydevmgr/resources/templateLamp.yml
pydevmgr/resources/templateManager.yml
pydevmgr/resources/templateMotor.yml
pydevmgr/resources/templatePiezo.yml
pydevmgr/resources/templateShutter.yml
pydevmgr/scripts/__init__.py
pydevmgr/scripts/dump.py
pydevmgr_core/__init__.py
pydevmgr_core/base.py
pydevmgr_core/com.py
pydevmgr_core/datamodel.py
pydevmgr_core/device.py
pydevmgr_core/download.py
pydevmgr_core/interface.py
pydevmgr_core/io.py
pydevmgr_core/manager.py
pydevmgr_core/node.py
pydevmgr_core/parser.py
pydevmgr_core/rpc.py
pydevmgr_core/toolbox.py
pydevmgr_core/upload.py
pydevmgr_core/wait.py
pydevmgr_elt/__init__.py
pydevmgr_elt/base/__init__.py
pydevmgr_elt/base/config.py
pydevmgr_elt/base/globalnode.py
pydevmgr_elt/base/io.py
pydevmgr_elt/base/tools.py
pydevmgr_elt/base/uacom.py
pydevmgr_elt/base/uadevice.py
pydevmgr_elt/base/uainterface.py
pydevmgr_elt/base/uamanager.py
pydevmgr_elt/base/uanode.py
pydevmgr_elt/base/uarpc.py
pydevmgr_elt/base/uarpcinterface.py
pydevmgr_elt/devices/__init__.py
pydevmgr-0.2.dist-info/METADATA
pydevmgr-0.2.dist-info/WHEEL
pydevmgr-0.2.dist-info/entry_points.txt
pydevmgr-0.2.dist-info/top_level.txt
pydevmgr-0.2.dist-info/RECORD
