Metadata-Version: 2.1
Name: pydevmgr
Version: 0.2
Summary: UNKNOWN
Home-page: UNKNOWN
Author: Sylvain Guieu
Author-email: sylvain.guieu@univ-grenoble-alpes.fr
License: Creative Commons Attribution-Noncommercial-Share Alike license
Platform: UNKNOWN
Requires-Dist: opcua
Requires-Dist: pyyaml
Requires-Dist: jinja2
Requires-Dist: argparse
Requires-Dist: cryptography
Requires-Dist: pydantic
